{"index.md":"BqAvjiy7","posts_analyticssdk.md":"CiZwc9jn","posts_api-cache.md":"CVNFEtCV","posts_architecture.md":"6KxC9P7J","posts_baoding.md":"B4e85m9I","posts_biketotibet.md":"DiIRdFa0","posts_block.md":"X8aBieOC","posts_car.md":"B95J_RCC","posts_carthage.md":"BZ4aLsO5","posts_cocoapods.md":"CZX1Sauq","posts_code-review.md":"BOcxhk3F","posts_cognition.md":"BQblwln4","posts_create-blog.md":"auiwfXnV","posts_design-patterns.md":"Bysosskt","posts_harmony1.md":"DBinUX-v","posts_harmony2.md":"DVjfQyuC","posts_harmony3.md":"DS5Lzmnu","posts_huashan.md":"Np6ST-23","posts_hugo.md":"DznwLC51","posts_huhehaote.md":"D_rHe76Z","posts_index.md":"8HfIY3ke","posts_ios-componentization.md":"Ctq5WUBc","posts_ios-design.md":"C0sFCgDe","posts_ios-life.md":"uwYllnFa","posts_ios-memory.md":"OnTRIzW0","posts_ios-task.md":"CXiapBGb","posts_ios-thread.md":"BaWiYk-U","posts_ios-tips.md":"DZga1FbZ","posts_job.md":"rPqX6sx8","posts_kaifeng.md":"DSQu9_Ax","posts_manage.md":"CwKSkJjl","posts_marquez.md":"DmA5XMLs","posts_moto.md":"DOHju8Lj","posts_nanjing.md":"CKSUQUNY","posts_qingzhou.md":"BHgPHWz4","posts_refactor.md":"oFsHhENF","posts_runtime.md":"Df2mLVfF","posts_sanfeng.md":"CIlmbN2H","posts_shan.md":"BQ01wkL_","posts_shandong.md":"DsiaAIUl","posts_shanghai.md":"CSzZ0Q6R","posts_shanxi.md":"B01_9U4H","posts_sichuan.md":"ULLahdDi","posts_sshkeys.md":"COwLZVhk","posts_suhang.md":"CxkGEZCZ","posts_swift.md":"KV11V8jy","posts_swiftui.md":"D_kqw4PA","posts_taizhou_tianjin.md":"C6Rwo-ye","posts_telegram-bot.md":"QI-iovXY","posts_ud.md":"n-EMkIsK","posts_xcframework.md":"s3SKbgH9","posts_xcodebuild.md":"DFGG245M","posts_xiaojiuguan.md":"C7rvr7at","posts_xinjiang.md":"CP9HMiWD","posts_xuzhou.md":"D578DPSo","posts_yubeng.md":"C3lpOEFn"}
